{
    "tPS17bcv_20170219_Gr13_Free_slit1.0_1_f.asci": {
        "Type": "SN IIn",
        "Redshift": "0.104",
        "Obs. Date": "2017-02-20",
        "Program": "PESSTO",
        "Contributor": "",
        "Bibcode": "",
        "Instrument": "ESO-NTT - EFOSC2-NTT",
        "Observer": "C. Barbarino, A. Nyholm",
        "Reducer": "F. Taddia, C. Fremling, J. Sollerman",
        "Reduction Status": "rapid",
        "Last Modified": "2017-02-20",
        "Modified By": "ilanm-UploadSet"
    }
}